README
setup.py
CubicReport.egg-info/PKG-INFO
CubicReport.egg-info/SOURCES.txt
CubicReport.egg-info/dependency_links.txt
CubicReport.egg-info/requires.txt
CubicReport.egg-info/top_level.txt
geraldo/__init__.py
geraldo/barcodes.py
geraldo/base.py
geraldo/cache.py
geraldo/charts.py
geraldo/cross_reference.py
geraldo/exceptions.py
geraldo/graphics.py
geraldo/models.py
geraldo/utils.py
geraldo/version.py
geraldo/widgets.py
geraldo/generators/__init__.py
geraldo/generators/base.py
geraldo/generators/csvgen.py
geraldo/generators/html.py
geraldo/generators/pdf.py
geraldo/generators/text.py
geraldo/generators/xmlstruct.py
geraldo/tests/__init__.py