Metadata-Version: 1.0
Name: CubicReport
Version: 0.4.18
Summary: CubicReport is a report engine based on Geraldo for Odoo, OpenERP, Python and Django applications
Home-page: http://www.cubicerp.com/
Author: Cubic ERP
Author-email: info@cubicerp.com
License: GNU Lesser General Public License (LGPL)
Platform: UNKNOWN
